{"data":{"school":{"id":"U2Nob29sLTE4MTQ=","name":"Cecil College"},"search":{"teachers":{"edges":[{"cursor":"YXJyYXljb25uZWN0aW9uOjA=","node":{"__typename":"Teacher","avgDifficulty":0,"avgRating":0,"courseCodes":[],"department":"Mathematics","firstName":"Alan","id":"VGVhY2hlci01ODQxNzk=","lastName":"Bass","numRatings":0,"school":{"id":"U2Nob29sLTE4MTQ=","name":"Cecil College"},"wouldTakeAgainPercent":-1}},{"cursor":"YXJyYXljb25uZWN0aW9uOjE=","node":{"__typename":"Teacher","avgDifficulty":0,"avgRating":0,"courseCodes":[],"department":"Nursing","firstName":"Lauren","id":"VGVhY2hlci0yNzc0Njky","lastName":"Dawson","numRatings":0,"school":{"id":"U2Nob29sLTE4MTQ=","name":"Cecil College"},"wouldTakeAgainPercent":-1}}],"resultCount":2}}}}

