{"data":{"school":{"id":"U2Nob29sLTQ1OTc=","name":"Southeastern University"},"search":{"teachers":{"edges":[{"cursor":"YXJyYXljb25uZWN0aW9uOjA=","node":{"__typename":"Teacher","avgDifficulty":2.9,"avgRating":4.5,"courseCodes":[{"courseCount":9,"courseName":"ISMA500"},{"courseCount":1,"courseName":"ISMA50001"}],"department":"Computer Science","firstName":"Saiid","id":"VGVhY2hlci0yNzg0NDk=","lastName":"Ganjalizadeh","numRatings":10,"school":{"id":"U2Nob29sLTQ1OTc=","name":"Southeastern University"},"wouldTakeAgainPercent":-1}},{"cursor":"YXJyYXljb25uZWN0aW9uOjE=","node":{"__typename":"Teacher","avgDifficulty":0,"avgRating":0,"courseCodes":[],"department":"Marketing","firstName":"John","id":"VGVhY2hlci0xMDkxNjIz","lastName":"Milton","numRatings":0,"school":{"id":"U2Nob29sLTQ1OTc=","name":"Southeastern University"},"wouldTakeAgainPercent":-1}},{"cursor":"YXJyYXljb25uZWN0aW9uOjI=","node":{"__typename":"Teacher","avgDifficulty":0,"avgRating":0,"courseCodes":[],"department":"Computer \u0026 Informational Tech.","firstName":"James","id":"VGVhY2hlci0xMTg2NTM1","lastName":"Kutz","numRatings":0,"school":{"id":"U2Nob29sLTQ1OTc=","name":"Southeastern University"},"wouldTakeAgainPercent":-1}},{"cursor":"YXJyYXljb25uZWN0aW9uOjM=","node":{"__typename":"Teacher","avgDifficulty":0,"avgRating":0,"courseCodes":[],"department":"Business","firstName":"Linda","id":"VGVhY2hlci0xMzM4NDYy","lastName":"Whitfield","numRatings":0,"school":{"id":"U2Nob29sLTQ1OTc=","name":"Southeastern University"},"wouldTakeAgainPercent":-1}},{"cursor":"YXJyYXljb25uZWN0aW9uOjQ=","node":{"__typename":"Teacher","avgDifficulty":0,"avgRating":0,"courseCodes":[],"department":"Business","firstName":"Ephraim","id":"VGVhY2hlci0xNjc1MDUz","lastName":"Okoro","numRatings":0,"school":{"id":"U2Nob29sLTQ1OTc=","name":"Southeastern University"},"wouldTakeAgainPercent":-1}}],"resultCount":5}}}}

