{"data":{"school":{"id":"U2Nob29sLTEzMDg5","name":"Dallas Christian College"},"search":{"teachers":{"edges":[{"cursor":"YXJyYXljb25uZWN0aW9uOjA=","node":{"__typename":"Teacher","avgDifficulty":0,"avgRating":0,"courseCodes":[],"department":"Education","firstName":"David","id":"VGVhY2hlci04NjYyMDE=","lastName":"Christine","numRatings":0,"school":{"id":"U2Nob29sLTEzMDg5","name":"Dallas Christian College"},"wouldTakeAgainPercent":-1}},{"cursor":"YXJyYXljb25uZWN0aW9uOjE=","node":{"__typename":"Teacher","avgDifficulty":0,"avgRating":0,"courseCodes":[],"department":"Education","firstName":"Dana","id":"VGVhY2hlci04NjYyMDI=","lastName":"Jobe","numRatings":0,"school":{"id":"U2Nob29sLTEzMDg5","name":"Dallas Christian College"},"wouldTakeAgainPercent":-1}},{"cursor":"YXJyYXljb25uZWN0aW9uOjI=","node":{"__typename":"Teacher","avgDifficulty":2.8,"avgRating":4.1,"courseCodes":[{"courseCount":1,"courseName":"BIBL2310"},{"courseCount":1,"courseName":"BIBL3210"},{"courseCount":2,"courseName":"BIBL3311"}],"department":"Religion","firstName":"Mark","id":"VGVhY2hlci04NjY3NTk=","lastName":"Berrier","numRatings":4,"school":{"id":"U2Nob29sLTEzMDg5","name":"Dallas Christian College"},"wouldTakeAgainPercent":-1}},{"cursor":"YXJyYXljb25uZWN0aW9uOjM=","node":{"__typename":"Teacher","avgDifficulty":0,"avgRating":0,"courseCodes":[],"department":"Management","firstName":"George","id":"VGVhY2hlci04NjY3NjA=","lastName":"Filpansick","numRatings":0,"school":{"id":"U2Nob29sLTEzMDg5","name":"Dallas Christian College"},"wouldTakeAgainPercent":-1}},{"cursor":"YXJyYXljb25uZWN0aW9uOjQ=","node":{"__typename":"Teacher","avgDifficulty":2,"avgRating":5,"courseCodes":[{"courseCount":1,"courseName":"MISS3310"}],"department":"Religion","firstName":"Gary","id":"VGVhY2hlci04NjY3NjY=","lastName":"Hardy","numRatings":1,"school":{"id":"U2Nob29sLTEzMDg5","name":"Dallas Christian College"},"wouldTakeAgainPercent":100}},{"cursor":"YXJyYXljb25uZWN0aW9uOjU=","node":{"__typename":"Teacher","avgDifficulty":3,"avgRating":4.3,"courseCodes":[{"courseCount":1,"courseName":"MUSC1115"},{"courseCount":1,"courseName":"MUSC3323"},{"courseCount":1,"courseName":"WORSH101"}],"department":"Music","firstName":"Scott","id":"VGVhY2hlci04NjY3Njg=","lastName":"Spies","numRatings":3,"school":{"id":"U2Nob29sLTEzMDg5","name":"Dallas Christian College"},"wouldTakeAgainPercent":-1}},{"cursor":"YXJyYXljb25uZWN0aW9uOjY=","node":{"__typename":"Teacher","avgDifficulty":2,"avgRating":2.8,"courseCodes":[{"courseCount":1,"courseName":"HIST13111321"},{"courseCount":1,"courseName":"HISTSECT"}],"department":"History","firstName":"Dr. Anthony","id":"VGVhY2hlci04NjY3Njk=","lastName":"Springer","numRatings":2,"school":{"id":"U2Nob29sLTEzMDg5","name":"Dallas Christian College"},"wouldTakeAgainPercent":-1}},{"cursor":"YXJyYXljb25uZWN0aW9uOjc=","node":{"__typename":"Teacher","avgDifficulty":2.5,"avgRating":4.5,"courseCodes":[{"courseCount":2,"courseName":"CHRS10101020"}],"department":"Religion","firstName":"Mark","id":"VGVhY2hlci04NjY3NzA=","lastName":"Worley","numRatings":2,"school":{"id":"U2Nob29sLTEzMDg5","name":"Dallas Christian College"},"wouldTakeAgainPercent":100}},{"cursor":"YXJyYXljb25uZWN0aW9uOjg=","node":{"__typename":"Teacher","avgDifficulty":0,"avgRating":0,"courseCodes":[],"department":"Religion","firstName":"Eric","id":"VGVhY2hlci04NjY3NzE=","lastName":"Hinton","numRatings":0,"school":{"id":"U2Nob29sLTEzMDg5","name":"Dallas Christian College"},"wouldTakeAgainPercent":-1}},{"cursor":"YXJyYXljb25uZWN0aW9uOjk=","node":{"__typename":"Teacher","avgDifficulty":0,"avgRating":0,"courseCodes":[],"department":"Education","firstName":"Bruce","id":"VGVhY2hlci04NjY3NzI=","lastName":"Long","numRatings":0,"school":{"id":"U2Nob29sLTEzMDg5","name":"Dallas Christian College"},"wouldTakeAgainPercent":-1}},{"cursor":"YXJyYXljb25uZWN0aW9uOjEw","node":{"__typename":"Teacher","avgDifficulty":3.5,"avgRating":5,"courseCodes":[{"courseCount":1,"courseName":"BIBL13321331"}],"department":"Religion","firstName":"Jon","id":"VGVhY2hlci04NjczMDU=","lastName":"Nelson Bailey","numRatings":2,"school":{"id":"U2Nob29sLTEzMDg5","name":"Dallas Christian College"},"wouldTakeAgainPercent":-1}},{"cursor":"YXJyYXljb25uZWN0aW9uOjEx","node":{"__typename":"Teacher","avgDifficulty":3.5,"avgRating":4,"courseCodes":[{"courseCount":1,"courseName":"HIST1301"}],"department":"History","firstName":"Mark","id":"VGVhY2hlci0xNDg0NDA4","lastName":"Fish","numRatings":2,"school":{"id":"U2Nob29sLTEzMDg5","name":"Dallas Christian College"},"wouldTakeAgainPercent":-1}},{"cursor":"YXJyYXljb25uZWN0aW9uOjEy","node":{"__typename":"Teacher","avgDifficulty":1,"avgRating":5,"courseCodes":[{"courseCount":1,"courseName":"BIBL1332"}],"department":"Religion","firstName":"Kristy","id":"VGVhY2hlci0xNjEyMzYx","lastName":"Thurmond","numRatings":1,"school":{"id":"U2Nob29sLTEzMDg5","name":"Dallas Christian College"},"wouldTakeAgainPercent":-1}},{"cursor":"YXJyYXljb25uZWN0aW9uOjEz","node":{"__typename":"Teacher","avgDifficulty":0,"avgRating":0,"courseCodes":[],"department":"Philosophy","firstName":"Kyle","id":"VGVhY2hlci0xODk4MzQ4","lastName":"Martin","numRatings":0,"school":{"id":"U2Nob29sLTEzMDg5","name":"Dallas Christian College"},"wouldTakeAgainPercent":-1}},{"cursor":"YXJyYXljb25uZWN0aW9uOjE0","node":{"__typename":"Teacher","avgDifficulty":3,"avgRating":5,"courseCodes":[{"courseCount":1,"courseName":"ACCT3301"}],"department":"Accounting","firstName":"John","id":"VGVhY2hlci0yMzU2NzE5","lastName":"Dewey","numRatings":1,"school":{"id":"U2Nob29sLTEzMDg5","name":"Dallas Christian College"},"wouldTakeAgainPercent":100}},{"cursor":"YXJyYXljb25uZWN0aW9uOjE1","node":{"__typename":"Teacher","avgDifficulty":0,"avgRating":0,"courseCodes":[],"department":"Religion","firstName":"Greg","id":"VGVhY2hlci0yMzU4Mjky","lastName":"Parks","numRatings":0,"school":{"id":"U2Nob29sLTEzMDg5","name":"Dallas Christian College"},"wouldTakeAgainPercent":-1}},{"cursor":"YXJyYXljb25uZWN0aW9uOjE2","node":{"__typename":"Teacher","avgDifficulty":2,"avgRating":1.5,"courseCodes":[{"courseCount":2,"courseName":"CHED1000"},{"courseCount":1,"courseName":"CHED1315"},{"courseCount":1,"courseName":"EDUC4361"}],"department":"Education","firstName":"Caroline","id":"VGVhY2hlci04NjY3NTE=","lastName":"Worley","numRatings":4,"school":{"id":"U2Nob29sLTEzMDg5","name":"Dallas Christian College"},"wouldTakeAgainPercent":0}},{"cursor":"YXJyYXljb25uZWN0aW9uOjE3","node":{"__typename":"Teacher","avgDifficulty":4.5,"avgRating":3.8,"courseCodes":[{"courseCount":1,"courseName":"BIBL1311"},{"courseCount":2,"courseName":"BIBL3400"},{"courseCount":1,"courseName":"PSALM300"}],"department":"Religion","firstName":"Mark","id":"VGVhY2hlci04NjY3NjM=","lastName":"Hahlen","numRatings":4,"school":{"id":"U2Nob29sLTEzMDg5","name":"Dallas Christian College"},"wouldTakeAgainPercent":100}},{"cursor":"YXJyYXljb25uZWN0aW9uOjE4","node":{"__typename":"Teacher","avgDifficulty":4.3,"avgRating":4,"courseCodes":[{"courseCount":3,"courseName":"LIT300"}],"department":"English","firstName":"Dr. Cara","id":"VGVhY2hlci04NjY3Njc=","lastName":"Snyder","numRatings":3,"school":{"id":"U2Nob29sLTEzMDg5","name":"Dallas Christian College"},"wouldTakeAgainPercent":100}},{"cursor":"YXJyYXljb25uZWN0aW9uOjE5","node":{"__typename":"Teacher","avgDifficulty":0,"avgRating":0,"courseCodes":[],"department":"Psychology","firstName":"Lyndsey","id":"VGVhY2hlci0yNjk0NDY2","lastName":"Neal","numRatings":0,"school":{"id":"U2Nob29sLTEzMDg5","name":"Dallas Christian College"},"wouldTakeAgainPercent":-1}},{"cursor":"YXJyYXljb25uZWN0aW9uOjIw","node":{"__typename":"Teacher","avgDifficulty":4,"avgRating":1,"courseCodes":[{"courseCount":1,"courseName":"ENGL2000"}],"department":"English","firstName":"Melody","id":"VGVhY2hlci0yNDgzOTc0","lastName":"Trowell","numRatings":1,"school":{"id":"U2Nob29sLTEzMDg5","name":"Dallas Christian College"},"wouldTakeAgainPercent":0}}],"resultCount":21}}}}

