{"data":{"school":{"id":"U2Nob29sLTEzODI1","name":"Utah College of Dental Hygiene"},"search":{"teachers":{"edges":[{"cursor":"YXJyYXljb25uZWN0aW9uOjA=","node":{"__typename":"Teacher","avgDifficulty":0,"avgRating":0,"courseCodes":[],"department":"Health Science","firstName":"Shelley","id":"VGVhY2hlci0xOTgyMDk5","lastName":"Brown","numRatings":0,"school":{"id":"U2Nob29sLTEzODI1","name":"Utah College of Dental Hygiene"},"wouldTakeAgainPercent":-1}},{"cursor":"YXJyYXljb25uZWN0aW9uOjE=","node":{"__typename":"Teacher","avgDifficulty":0,"avgRating":0,"courseCodes":[],"department":"Health Science","firstName":"Brent","id":"VGVhY2hlci0yMTMyODA3","lastName":"Molen","numRatings":0,"school":{"id":"U2Nob29sLTEzODI1","name":"Utah College of Dental Hygiene"},"wouldTakeAgainPercent":-1}},{"cursor":"YXJyYXljb25uZWN0aW9uOjI=","node":{"__typename":"Teacher","avgDifficulty":3,"avgRating":5,"courseCodes":[{"courseCount":1,"courseName":"BMS2123"}],"department":"Education","firstName":"Jason","id":"VGVhY2hlci0yMTUxMTc4","lastName":"Allan","numRatings":1,"school":{"id":"U2Nob29sLTEzODI1","name":"Utah College of Dental Hygiene"},"wouldTakeAgainPercent":100}}],"resultCount":3}}}}

